LICENSE
MANIFEST.in
README.rst
setup.cfg
setup.py
brocade_plugins.egg-info/PKG-INFO
brocade_plugins.egg-info/SOURCES.txt
brocade_plugins.egg-info/dependency_links.txt
brocade_plugins.egg-info/not-zip-safe
brocade_plugins.egg-info/pbr.json
brocade_plugins.egg-info/requires.txt
brocade_plugins.egg-info/top_level.txt
vyatta/__init__.py
vyatta/common/__init__.py
vyatta/common/config.py
vyatta/common/exceptions.py
vyatta/common/globals.py
vyatta/common/l3_agent.py
vyatta/common/parsers.py
vyatta/common/utils.py
vyatta/common/vrouter_config.py
vyatta/tests/__init__.py
vyatta/tests/test_vrouter_driver.py
vyatta/vrouter/__init__.py
vyatta/vrouter/client.py
vyatta/vrouter/driver.py
vyatta/vrouter/neutron_plugin.py