Metadata-Version: 1.1
Name: brocade-plugins
Version: 2015.1
Summary: Brocade Vyatta L3 router Neutron plugin
Home-page: UNKNOWN
Author: Brocade
Author-email: natarajk@brocade.com
License: Apache-2
Platform: UNKNOWN
Classifier: Environment :: OpenStack
Classifier: Intended Audience :: Information Technology
Classifier: Intended Audience :: System Administrators
Classifier: License :: OSI Approved :: Apache Software License
Classifier: Operating System :: POSIX :: Linux
Classifier: Programming Language :: Python
Classifier: Programming Language :: Python :: 2
Classifier: Programming Language :: Python :: 2.7
